multidb.py
multidb-0.1.4.dist-info/METADATA
multidb-0.1.4.dist-info/WHEEL
multidb-0.1.4.dist-info/top_level.txt
multidb-0.1.4.dist-info/RECORD
